odoo/addons/account_invoice_warn_message/README.rst
odoo/addons/account_invoice_warn_message/__init__.py
odoo/addons/account_invoice_warn_message/__manifest__.py
odoo/addons/account_invoice_warn_message/i18n/account_invoice_warn_message.pot
odoo/addons/account_invoice_warn_message/i18n/es.po
odoo/addons/account_invoice_warn_message/models/__init__.py
odoo/addons/account_invoice_warn_message/models/account_move.py
odoo/addons/account_invoice_warn_message/models/res_company.py
odoo/addons/account_invoice_warn_message/models/res_config_settings.py
odoo/addons/account_invoice_warn_message/readme/CONTRIBUTORS.rst
odoo/addons/account_invoice_warn_message/readme/DESCRIPTION.rst
odoo/addons/account_invoice_warn_message/static/description/icon.png
odoo/addons/account_invoice_warn_message/static/description/index.html
odoo/addons/account_invoice_warn_message/tests/__init__.py
odoo/addons/account_invoice_warn_message/tests/test_account_invoice_warn_message.py
odoo/addons/account_invoice_warn_message/views/account_move_views.xml
odoo/addons/account_invoice_warn_message/views/res_config_settings_views.xml
odoo13_addon_account_invoice_warn_message-13.0.2.0.0.dist-info/METADATA
odoo13_addon_account_invoice_warn_message-13.0.2.0.0.dist-info/WHEEL
odoo13_addon_account_invoice_warn_message-13.0.2.0.0.dist-info/top_level.txt
odoo13_addon_account_invoice_warn_message-13.0.2.0.0.dist-info/RECORD
